{
	"id": "9hEKeLrsg57Z77T",
	"json": "{\"id\":\"9hEKeLrsg57Z77T\",\"url\":\"https://github.com/srizzon/git-city\",\"loadedUrl\":\"https://github.com/srizzon/git-city\",\"uniqueKey\":\"https://github.com/srizzon/git-city\",\"method\":\"GET\",\"noRetry\":false,\"retryCount\":0,\"errorMessages\":[],\"headers\":{},\"userData\":{\"__crawlee\":{\"state\":4}},\"handledAt\":\"2026-03-13T20:28:27.088Z\"}",
	"method": "GET",
	"orderNo": null,
	"retryCount": 0,
	"uniqueKey": "https://github.com/srizzon/git-city",
	"url": "https://github.com/srizzon/git-city"
}